latoken/__init__.py
latoken/client.py
latoken/enums.py
latoken/helpers.py
python_latoken-0.2.1.dist-info/LICENSE
python_latoken-0.2.1.dist-info/METADATA
python_latoken-0.2.1.dist-info/WHEEL
python_latoken-0.2.1.dist-info/top_level.txt
python_latoken-0.2.1.dist-info/RECORD
