Metadata-Version: 2.1
Name: python-latoken
Version: 0.2.1
Summary: LATOKEN REST API and STOMP Websocket python implementation
Home-page: https://github.com/purveyor97/python_latoken
Author: Nikita Oleinik
License: MIT
Keywords: latoken exchange rest websockets api crypto bitcoin trading
Platform: UNKNOWN
Classifier: Intended Audience :: Developers
Classifier: Programming Language :: Python :: 3
Classifier: Programming Language :: Python :: 3.7
Classifier: Programming Language :: Python :: 3.8
Classifier: Programming Language :: Python :: 3.9
Classifier: License :: OSI Approved :: MIT License
Classifier: Operating System :: OS Independent
License-File: LICENSE
Requires-Dist: requests
Requires-Dist: stomper
Requires-Dist: websocket-client
